oh_to_smartplug_energy_controller/.gitignore
oh_to_smartplug_energy_controller/config.yml
oh_to_smartplug_energy_controller/entry_point.py
oh_to_smartplug_energy_controller/logging.yml
oh_to_smartplug_energy_controller/rules/habapp_rules.py
smartplug_energy_controller/__init__.py
smartplug_energy_controller/app.py
smartplug_energy_controller/config.py
smartplug_energy_controller/plug_controller.py
smartplug_energy_controller/plug_manager.py
smartplug_energy_controller/utils.py
smartplug_energy_controller-0.1.7.dist-info/LICENSE
smartplug_energy_controller-0.1.7.dist-info/METADATA
smartplug_energy_controller-0.1.7.dist-info/WHEEL
smartplug_energy_controller-0.1.7.dist-info/entry_points.txt
smartplug_energy_controller-0.1.7.dist-info/RECORD
