Metadata-Version: 2.3
Name: smartplug_energy_controller
Version: 0.1.7
Summary: Turning smartplugs on/off depending on current electricity consumption
Author: Heiko Bauer
Author-email: heiko_bauer@icloud.com
Requires-Python: >=3.11,<4.0
Classifier: Programming Language :: Python :: 3
Classifier: Programming Language :: Python :: 3.11
Classifier: Programming Language :: Python :: 3.12
Classifier: Programming Language :: Python :: 3.13
Requires-Dist: apscheduler (>=3.11.0,<4.0.0)
Requires-Dist: fastapi (>=0.111.0,<0.112.0)
Requires-Dist: habapp (==24.2.0)
Requires-Dist: plugp100 (>=5.1.3,<6.0.0)
Requires-Dist: pydantic-settings (>=2.2.1,<3.0.0)
Requires-Dist: python-dotenv (>=1.0.1,<2.0.0)
Requires-Dist: ruamel-yaml (>=0.18.6,<0.19.0)
Requires-Dist: typing-inspect (>=0.9.0,<0.10.0)
Requires-Dist: uvicorn (>=0.28.0,<0.29.0)
Project-URL: Repository, https://github.com/die-bauerei/smartplug-energy-controller
